pytestTestreport/__init__.py
pytestTestreport/pytest_testreport.py
pytestTestreport/templates/__init__.py
pytestTestreport/templates/templates.html
pytestTestreport/templates/templates2.html
pytest_testreport-1.1.6.dist-info/LICENSE
pytest_testreport-1.1.6.dist-info/METADATA
pytest_testreport-1.1.6.dist-info/WHEEL
pytest_testreport-1.1.6.dist-info/entry_points.txt
pytest_testreport-1.1.6.dist-info/top_level.txt
pytest_testreport-1.1.6.dist-info/RECORD
